OCR/__init__.py
OCR/getCor.py
OCR/fonts/simfang.ttf
OCR/imgs_en/A93.jpg
OCR/imgs_en/androidAlbum.jpeg
OCR/imgs_en/androidInstall.png
OCR/imgs_en/huazhii.png
OCR/imgs_en/menu.png
mtpdocr-0.1.4.dist-info/METADATA
mtpdocr-0.1.4.dist-info/WHEEL
mtpdocr-0.1.4.dist-info/entry_points.txt
mtpdocr-0.1.4.dist-info/top_level.txt
mtpdocr-0.1.4.dist-info/zip-safe
mtpdocr-0.1.4.dist-info/RECORD
