Metadata-Version: 2.1
Name: mtpdocr
Version: 0.1.4
Summary: OCR
Home-page: https://github.com/AllenCall/paddleOCRDemo
Author: allen
Author-email: 310315734@qq.com
License: MIT
Keywords: python OCR base on paddleOCR
Platform: UNKNOWN
Requires-Dist: paddleocr (==2.2)
Requires-Dist: paddlepaddle
